setup.py
my_env_points/__init__.py
my_env_points.egg-info/PKG-INFO
my_env_points.egg-info/SOURCES.txt
my_env_points.egg-info/dependency_links.txt
my_env_points.egg-info/requires.txt
my_env_points.egg-info/top_level.txt
my_env_points/envs/__init__.py
my_env_points/envs/point_env.py
my_env_points/wrappers/__init__.py