Metadata-Version: 2.1
Name: my-env-points
Version: 0.0.6
Requires-Dist: gymnasium==0.29.1
